{"month":"2024-11","funder":13476,"topic":"campaign-finance","total_keywords":8,"keywords":{"ab0f4de8":{"keyword":"girls","count":2,"weighted_score":1.2,"ad_ids":[[8110,8111]]},"e0988936":{"keyword":"long day","count":2,"weighted_score":1.2,"ad_ids":[[8110,8111]]},"642fda95":{"keyword":"intelligent questions","count":2,"weighted_score":1.2,"ad_ids":[[8110,8111]]},"2ad1281f":{"keyword":"bringing us pizza","count":2,"weighted_score":1.2,"ad_ids":[[8110,8111]]},"4ea14058":{"keyword":"home","count":2,"weighted_score":1.2,"ad_ids":[[8110,8111]]},"486ea462":{"keyword":"world","count":2,"weighted_score":1.2,"ad_ids":[[8110,8111]]},"7d9a7a69":{"keyword":"have any questions","count":1,"weighted_score":1.13,"ad_ids":[8112]},"0895a532":{"keyword":"give","count":1,"weighted_score":1.13,"ad_ids":[8112]}}}