{"month":"2023-09","funder":1605,"total_keywords":40,"keywords":{"dbf0dfb0":{"keyword":"prochains coups","count":2,"weighted_score":1.2,"ad_ids":[[21701,21702]]},"5c5c90b3":{"keyword":"marchands","count":6,"weighted_score":1.36,"ad_ids":[21703,[21732,21735],21737]},"ceb66abf":{"keyword":"grande qualit\u00e9","count":1,"weighted_score":1.13,"ad_ids":[21703]},"a9825694":{"keyword":"voir marchands","count":1,"weighted_score":1.13,"ad_ids":[21703]},"25bf8e1a":{"keyword":"local","count":2,"weighted_score":1.2,"ad_ids":[21703,21733]},"23367984":{"keyword":"match parfait","count":9,"weighted_score":1.42,"ad_ids":[[21704,21705],[21707,21710],[21724,21725],21731]},"793ba416":{"keyword":"grand march\u00e9","count":35,"weighted_score":1.66,"ad_ids":[[21704,21738]]},"70d9b4cb":{"keyword":"bonne bouffe","count":4,"weighted_score":1.3,"ad_ids":[21705,[21707,21708],21731]},"c55dc839":{"keyword":"sortie r\u00e9ussie","count":4,"weighted_score":1.3,"ad_ids":[21705,[21707,21708],21731]},"2c14b85c":{"keyword":"pas d'ici","count":1,"weighted_score":1.13,"ad_ids":[21706]},"0a2bb0aa":{"keyword":"cultiv\u00e9s \u00e0","count":1,"weighted_score":1.13,"ad_ids":[21706]},"9fbb5c05":{"keyword":"venez rencontrer nos artisans","count":1,"weighted_score":1.13,"ad_ids":[21706]},"942ff090":{"keyword":"explorez notre s\u00e9lection de fruits et","count":1,"weighted_score":1.13,"ad_ids":[21706]},"4250c946":{"keyword":"les ingr\u00e9dients n\u00e9cessaires pour","count":1,"weighted_score":1.13,"ad_ids":[21706]},"a9a91f78":{"keyword":"de saison","count":1,"weighted_score":1.13,"ad_ids":[21706]},"f6fedd1b":{"keyword":"votre destination","count":1,"weighted_score":1.13,"ad_ids":[21706]},"8849e9cf":{"keyword":"produits frais","count":1,"weighted_score":1.13,"ad_ids":[21706]},"575e8900":{"keyword":"incontournable pour savourer des","count":1,"weighted_score":1.13,"ad_ids":[21706]},"1b8bfb4d":{"keyword":"ainsi que tous","count":1,"weighted_score":1.13,"ad_ids":[21706]},"204481df":{"keyword":"appuyez pour","count":1,"weighted_score":1.13,"ad_ids":[21706]},"a9e4a1d1":{"keyword":"recettes inspirantes et cr\u00e9er un festin","count":1,"weighted_score":1.13,"ad_ids":[21706]},"c1ab1085":{"keyword":"le grand march\u00e9","count":3,"weighted_score":1.26,"ad_ids":[21706,21719,21729]},"f228f887":{"keyword":"cr\u00e9er festin","count":8,"weighted_score":1.41,"ad_ids":[[21711,21714],21721,21726,21728,21730]},"4b6299ed":{"keyword":"concocter recettes","count":8,"weighted_score":1.41,"ad_ids":[[21711,21714],21721,21726,21728,21730]},"ee60e63e":{"keyword":"savourer produits","count":8,"weighted_score":1.41,"ad_ids":[[21711,21714],21721,21726,21728,21730]},"36a5573d":{"keyword":"soir\u00e9e r\u00e9ussie","count":4,"weighted_score":1.3,"ad_ids":[[21713,21714],21721,21730]},"03c44e36":{"keyword":"faire connaissance","count":4,"weighted_score":1.3,"ad_ids":[21715,21717,21723,21727]},"f184917a":{"keyword":"visitant l\u2019","count":4,"weighted_score":1.3,"ad_ids":[21716,21718,21720,21722]},"7e953e6a":{"keyword":"rencontrer gens","count":4,"weighted_score":1.3,"ad_ids":[21716,21718,21720,21722]},"55697242":{"keyword":"passe","count":2,"weighted_score":1.2,"ad_ids":[21719,21729]},"ccdca72e":{"keyword":"que \u00e7a se passe","count":2,"weighted_score":1.2,"ad_ids":[21719,21729]},"fcaa375d":{"keyword":"c'est l\u00e0","count":2,"weighted_score":1.2,"ad_ids":[21719,21729]},"2d51c11e":{"keyword":"vos prochains soupers","count":2,"weighted_score":1.2,"ad_ids":[21719,21729]},"e602fcbf":{"keyword":"pour faire une bonne","count":2,"weighted_score":1.2,"ad_ids":[21719,21729]},"11ae6165":{"keyword":"des bonnes p\u00e2tes","count":2,"weighted_score":1.2,"ad_ids":[21719,21729]},"eba03f6c":{"keyword":"c'est l\u00e0 que \u00e7a se","count":2,"weighted_score":1.2,"ad_ids":[21719,21729]},"80e95980":{"keyword":"vous voulez frapper fort","count":2,"weighted_score":1.2,"ad_ids":[21719,21729]},"6647d77f":{"keyword":"bonnes brochettes","count":2,"weighted_score":1.2,"ad_ids":[21719,21729]},"94c72e2f":{"keyword":"vergers turcotte","count":1,"weighted_score":1.13,"ad_ids":[21733]},"d2ead4ad":{"keyword":"activit\u00e9s","count":4,"weighted_score":1.3,"ad_ids":[[21734,21735],[21737,21738]]}}}