{"month":"2024-10","funder":125,"topic":"anti-woke","total_keywords":234,"keywords":{"e3b0c442":{"keyword":"","count":1,"weighted_score":1.13,"ad_ids":[14956]},"f8a14f81":{"keyword":"trudeau","count":2,"weighted_score":1.2,"ad_ids":[14963,14979]},"408c7c58":{"keyword":"canada","count":7,"weighted_score":1.38,"ad_ids":[[14963,14964],14975,14979,[14981,14982],14990]},"b1decd31":{"keyword":"justin trudeau","count":2,"weighted_score":1.2,"ad_ids":[14963,14979]},"ab627e25":{"keyword":"historical fact","count":1,"weighted_score":1.13,"ad_ids":[14964]},"1bd4a1de":{"keyword":"powell river","count":4,"weighted_score":1.3,"ad_ids":[14964,14971,[14976,14977]]},"84397758":{"keyword":"full story","count":13,"weighted_score":1.49,"ad_ids":[14964,14966,14971,[14975,14977],[14981,14983],[14986,14988],14990]},"4f244f00":{"keyword":"basic freedoms","count":1,"weighted_score":1.13,"ad_ids":[14964]},"e61c7508":{"keyword":"british columbians","count":1,"weighted_score":1.13,"ad_ids":[14964]},"f520a164":{"keyword":"public opinion","count":1,"weighted_score":1.13,"ad_ids":[14964]},"3fe973c9":{"keyword":"very foundation","count":1,"weighted_score":1.13,"ad_ids":[14964]},"c74fe87c":{"keyword":"change the name","count":1,"weighted_score":1.13,"ad_ids":[14964]},"1e7dc6d6":{"keyword":"fact","count":1,"weighted_score":1.13,"ad_ids":[14964]},"4a3a9b49":{"keyword":"risky business","count":1,"weighted_score":1.13,"ad_ids":[14964]},"3316348d":{"keyword":"read","count":14,"weighted_score":1.5,"ad_ids":[14964,14966,14971,[14974,14977],[14981,14983],[14986,14988],14990]},"ebf2105c":{"keyword":"public discussions","count":1,"weighted_score":1.13,"ad_ids":[14964]},"21a64753":{"keyword":"frances widdowson","count":1,"weighted_score":1.13,"ad_ids":[14964]},"1da61934":{"keyword":"includes the denunciation","count":1,"weighted_score":1.13,"ad_ids":[14964]},"3d5394a6":{"keyword":"vicious debate","count":1,"weighted_score":1.13,"ad_ids":[14964]},"7470eada":{"keyword":"canadians","count":2,"weighted_score":1.2,"ad_ids":[14964,14981]},"9ff3297e":{"keyword":"fundamental freedoms","count":1,"weighted_score":1.13,"ad_ids":[14964]},"35cce0a1":{"keyword":"cost you","count":1,"weighted_score":1.13,"ad_ids":[14966]},"7e1f2ed0":{"keyword":"personal opposition","count":1,"weighted_score":1.13,"ad_ids":[14966]},"bd1ad109":{"keyword":"democratic process","count":1,"weighted_score":1.13,"ad_ids":[14966]},"4a0a339b":{"keyword":"personal","count":2,"weighted_score":1.2,"ad_ids":[14966,14974]},"f185b45f":{"keyword":"political objective","count":1,"weighted_score":1.13,"ad_ids":[14966]},"c062172f":{"keyword":"is no record","count":1,"weighted_score":1.13,"ad_ids":[14966]},"153f894d":{"keyword":"canadian citizen","count":1,"weighted_score":1.13,"ad_ids":[14966]},"6519a601":{"keyword":"dramatic punishment","count":1,"weighted_score":1.13,"ad_ids":[14966]},"5b455b68":{"keyword":"told the new westminster times","count":2,"weighted_score":1.2,"ad_ids":[14966,14975]},"2471368f":{"keyword":"had any issues","count":1,"weighted_score":1.13,"ad_ids":[14971]},"493eb17f":{"keyword":"few months","count":1,"weighted_score":1.13,"ad_ids":[14971]},"10b9178e":{"keyword":"violating the board","count":1,"weighted_score":1.13,"ad_ids":[14971]},"62b4b2fc":{"keyword":"board superintendent","count":1,"weighted_score":1.13,"ad_ids":[14971]},"1d6f4fa0":{"keyword":"regarding the name change","count":1,"weighted_score":1.13,"ad_ids":[14971]},"c1b1e5dd":{"keyword":"mass graves","count":1,"weighted_score":1.13,"ad_ids":[14971]},"8ce69cb5":{"keyword":"possibility burroughs","count":1,"weighted_score":1.13,"ad_ids":[14971]},"e093849b":{"keyword":"name change","count":2,"weighted_score":1.2,"ad_ids":[14971,14977]},"1a8e38b4":{"keyword":"question the existence","count":1,"weighted_score":1.13,"ad_ids":[14971]},"ca640a1e":{"keyword":"was the comment","count":1,"weighted_score":1.13,"ad_ids":[14971]},"3e860f41":{"keyword":"social","count":2,"weighted_score":1.2,"ad_ids":[14971,14989]},"40d153cc":{"keyword":"brian burroughs","count":1,"weighted_score":1.13,"ad_ids":[14971]},"96726f43":{"keyword":"social media","count":2,"weighted_score":1.2,"ad_ids":[14971,14989]},"25bf8e1a":{"keyword":"local","count":1,"weighted_score":1.13,"ad_ids":[14971]},"2f3adcdd":{"keyword":"local school board","count":1,"weighted_score":1.13,"ad_ids":[14971]},"a7c58e12":{"keyword":"residential schools","count":1,"weighted_score":1.13,"ad_ids":[14971]},"045b37d6":{"keyword":"greatest trick","count":1,"weighted_score":1.13,"ad_ids":[14974]},"5c8201cb":{"keyword":"convincing the world","count":1,"weighted_score":1.13,"ad_ids":[14974]},"1495cc13":{"keyword":"very existence","count":1,"weighted_score":1.13,"ad_ids":[14974]},"2a230bdd":{"keyword":"same thing","count":1,"weighted_score":1.13,"ad_ids":[14974]},"3358397e":{"keyword":"scholarly research","count":1,"weighted_score":1.13,"ad_ids":[14974]},"1f724890":{"keyword":"poisonous phenomenon","count":1,"weighted_score":1.13,"ad_ids":[14974]},"3c18a125":{"keyword":"collin may","count":2,"weighted_score":1.2,"ad_ids":[14974,14984]},"139bc52d":{"keyword":"dangerous thing","count":1,"weighted_score":1.13,"ad_ids":[14974]},"568502c9":{"keyword":"very existe","count":1,"weighted_score":1.13,"ad_ids":[14974]},"66a80ab6":{"keyword":"wokist demands","count":1,"weighted_score":1.13,"ad_ids":[14974]},"a3055c97":{"keyword":"read more","count":1,"weighted_score":1.13,"ad_ids":[14974]},"3c00192f":{"keyword":"own actions","count":1,"weighted_score":1.13,"ad_ids":[14974]},"1bbb5074":{"keyword":"modern_day scourge","count":1,"weighted_score":1.13,"ad_ids":[14974]},"0bcd36de":{"keyword":"personal experience","count":1,"weighted_score":1.13,"ad_ids":[14974]},"c3e051cf":{"keyword":"community accord","count":1,"weighted_score":1.13,"ad_ids":[14975]},"c9022680":{"keyword":"people","count":4,"weighted_score":1.3,"ad_ids":[14975,14977,14981,14986]},"44618863":{"keyword":"certain group","count":1,"weighted_score":1.13,"ad_ids":[14975]},"22412f12":{"keyword":"used the term","count":1,"weighted_score":1.13,"ad_ids":[14975]},"a6609916":{"keyword":"poorer treatment","count":1,"weighted_score":1.13,"ad_ids":[14975]},"023cd16f":{"keyword":"obvious instance","count":1,"weighted_score":1.13,"ad_ids":[14975]},"31ecea16":{"keyword":"past february","count":1,"weighted_score":1.13,"ad_ids":[14975]},"7ea3baaa":{"keyword":"white people","count":1,"weighted_score":1.13,"ad_ids":[14975]},"ab04be94":{"keyword":"fewer rights","count":1,"weighted_score":1.13,"ad_ids":[14975]},"f5d374e3":{"keyword":"entire name_change process","count":1,"weighted_score":1.13,"ad_ids":[14975]},"3ca7ddd4":{"keyword":"times editor david brett","count":1,"weighted_score":1.13,"ad_ids":[14975]},"9afd4652":{"keyword":"public racism","count":1,"weighted_score":1.13,"ad_ids":[14975]},"b858da05":{"keyword":"racist statements","count":1,"weighted_score":1.13,"ad_ids":[14976]},"8b54bbc1":{"keyword":"something paramedics","count":1,"weighted_score":1.13,"ad_ids":[14976]},"c8ffc8f3":{"keyword":"bc emergency health services","count":1,"weighted_score":1.13,"ad_ids":[14976]},"62484e22":{"keyword":"health","count":1,"weighted_score":1.13,"ad_ids":[14976]},"e4de53b4":{"keyword":"ted vizzutti","count":1,"weighted_score":1.13,"ad_ids":[14976]},"cb04d058":{"keyword":"graceful exit","count":1,"weighted_score":1.13,"ad_ids":[14976]},"5f72b623":{"keyword":"disciplinary action","count":1,"weighted_score":1.13,"ad_ids":[14976]},"759a0d5e":{"keyword":"health services","count":1,"weighted_score":1.13,"ad_ids":[14976]},"fc56a64a":{"keyword":"took the advice","count":1,"weighted_score":1.13,"ad_ids":[14976]},"c878865e":{"keyword":"disciplinary meeting","count":1,"weighted_score":1.13,"ad_ids":[14976]},"90829360":{"keyword":"expensive fight","count":1,"weighted_score":1.13,"ad_ids":[14976]},"9da4925c":{"keyword":"health care","count":1,"weighted_score":1.13,"ad_ids":[14976]},"63a0106b":{"keyword":"kamloops residential school","count":1,"weighted_score":1.13,"ad_ids":[14977]},"27780590":{"keyword":"colonial policy","count":1,"weighted_score":1.13,"ad_ids":[14977]},"bbfa0827":{"keyword":"israel powell","count":1,"weighted_score":1.13,"ad_ids":[14977]},"dd51a825":{"keyword":"mayor","count":1,"weighted_score":1.13,"ad_ids":[14977]},"4def961e":{"keyword":"recent finding","count":1,"weighted_score":1.13,"ad_ids":[14977]},"e756c650":{"keyword":"outlawing the potlatch","count":1,"weighted_score":1.13,"ad_ids":[14977]},"a8810b32":{"keyword":"cooperative tone","count":1,"weighted_score":1.13,"ad_ids":[14977]},"8aaff1b2":{"keyword":"john hackett","count":1,"weighted_score":1.13,"ad_ids":[14977]},"295c5409":{"keyword":"deny the truth","count":1,"weighted_score":1.13,"ad_ids":[14977]},"ee13792d":{"keyword":"had no intention","count":1,"weighted_score":1.13,"ad_ids":[14977]},"96d9632f":{"keyword":"john","count":1,"weighted_score":1.13,"ad_ids":[14977]},"65e65486":{"keyword":"residential school policy","count":1,"weighted_score":1.13,"ad_ids":[14977]},"db28d475":{"keyword":"follow_up letter","count":1,"weighted_score":1.13,"ad_ids":[14977]},"2315d3ad":{"keyword":"new sense","count":1,"weighted_score":1.13,"ad_ids":[14977]},"c3b8c908":{"keyword":"western canada","count":1,"weighted_score":1.13,"ad_ids":[14979]},"10bf4be8":{"keyword":"crisis_communication expert evan nierman","count":1,"weighted_score":1.13,"ad_ids":[14980]},"15a1d693":{"keyword":"cancel culture curse","count":1,"weighted_score":1.13,"ad_ids":[14980]},"221b3b90":{"keyword":"moral posturing","count":1,"weighted_score":1.13,"ad_ids":[14980]},"3734aebd":{"keyword":"key elements","count":1,"weighted_score":1.13,"ad_ids":[14980]},"7c4a198d":{"keyword":"predictable pattern","count":1,"weighted_score":1.13,"ad_ids":[14980]},"01e95936":{"keyword":"exposes the psychology","count":1,"weighted_score":1.13,"ad_ids":[14980]},"bf3203d6":{"keyword":"true cancellation events","count":1,"weighted_score":1.13,"ad_ids":[14980]},"294ba825":{"keyword":"general statement","count":1,"weighted_score":1.13,"ad_ids":[14981]},"0bde9fd3":{"keyword":"indigenous reconciliation","count":1,"weighted_score":1.13,"ad_ids":[14981]},"aaecda30":{"keyword":"hamas terror attack","count":1,"weighted_score":1.13,"ad_ids":[14981]},"b7fee531":{"keyword":"recent in_service","count":1,"weighted_score":1.13,"ad_ids":[14981]},"9c19636d":{"keyword":"come","count":1,"weighted_score":1.13,"ad_ids":[14981]},"31eed9c6":{"keyword":"settler colonialism","count":1,"weighted_score":1.13,"ad_ids":[14981]},"8a0f0f6a":{"keyword":"essential subtext","count":1,"weighted_score":1.13,"ad_ids":[14981]},"8df68761":{"keyword":"educational theorist","count":1,"weighted_score":1.13,"ad_ids":[14981]},"65342c8a":{"keyword":"land back","count":5,"weighted_score":1.33,"ad_ids":[[14981,14982],[14987,14988],14990]},"dfe259df":{"keyword":"non_indigenous canadians","count":1,"weighted_score":1.13,"ad_ids":[14981]},"5e29c99e":{"keyword":"guest speaker christopher emdin","count":1,"weighted_score":1.13,"ad_ids":[14981]},"4261a2e0":{"keyword":"settler colonialists","count":2,"weighted_score":1.2,"ad_ids":[[14981,14982]]},"b01748c7":{"keyword":"indigenous education","count":1,"weighted_score":1.13,"ad_ids":[14981]},"8cb91141":{"keyword":"indigenous people","count":1,"weighted_score":1.13,"ad_ids":[14981]},"6771e5af":{"keyword":"current oppressor","count":1,"weighted_score":1.13,"ad_ids":[14981]},"43060e63":{"keyword":"pedagogical angst","count":1,"weighted_score":1.13,"ad_ids":[14981]},"f434d56d":{"keyword":"teachers","count":1,"weighted_score":1.13,"ad_ids":[14981]},"c92ad77d":{"keyword":"colonial occupation","count":1,"weighted_score":1.13,"ad_ids":[14981]},"dba36bff":{"keyword":"words","count":1,"weighted_score":1.13,"ad_ids":[14981]},"6dbd186e":{"keyword":"giant display screen","count":1,"weighted_score":1.13,"ad_ids":[14981]},"007d73b0":{"keyword":"have a right","count":1,"weighted_score":1.13,"ad_ids":[14981]},"0512c9ea":{"keyword":"american author","count":1,"weighted_score":1.13,"ad_ids":[14981]},"f5e72478":{"keyword":"become a source","count":1,"weighted_score":1.13,"ad_ids":[14981]},"f081c9d6":{"keyword":"manitoba teachers","count":1,"weighted_score":1.13,"ad_ids":[14981]},"e14ddf2a":{"keyword":"winnipeg school division","count":1,"weighted_score":1.13,"ad_ids":[14981]},"981e5b39":{"keyword":"united states","count":2,"weighted_score":1.2,"ad_ids":[14982,14990]},"379e15d3":{"keyword":"blood tribe","count":1,"weighted_score":1.13,"ad_ids":[14982]},"84411ff2":{"keyword":"black hills","count":1,"weighted_score":1.13,"ad_ids":[14982]},"1ec54b14":{"keyword":"south dakota","count":1,"weighted_score":1.13,"ad_ids":[14982]},"5dd5630e":{"keyword":"racial nationalism","count":1,"weighted_score":1.13,"ad_ids":[14982]},"6bb1831d":{"keyword":"sovereign territory","count":1,"weighted_score":1.13,"ad_ids":[14982]},"17845ff9":{"keyword":"militant iteration","count":1,"weighted_score":1.13,"ad_ids":[14982]},"7a9f7e0f":{"keyword":"land back proponents","count":1,"weighted_score":1.13,"ad_ids":[14982]},"8dd511e5":{"keyword":"disavow the legitimacy","count":1,"weighted_score":1.13,"ad_ids":[14982]},"22c26429":{"keyword":"new zealand","count":1,"weighted_score":1.13,"ad_ids":[14982]},"317c6b6e":{"keyword":"arnell tailfeathers","count":1,"weighted_score":1.13,"ad_ids":[14982]},"203b6c56":{"keyword":"explicit expression","count":1,"weighted_score":1.13,"ad_ids":[14982]},"72e219d3":{"keyword":"tribal control","count":1,"weighted_score":1.13,"ad_ids":[14982]},"2ad587b4":{"keyword":"demanding the reversion","count":1,"weighted_score":1.13,"ad_ids":[14982]},"9bb21906":{"keyword":"aboriginal nationalism","count":1,"weighted_score":1.13,"ad_ids":[14982]},"684de6b4":{"keyword":"mount rushmore","count":1,"weighted_score":1.13,"ad_ids":[14982]},"310ec20f":{"keyword":"gender studies","count":1,"weighted_score":1.13,"ad_ids":[14983]},"13281f5a":{"keyword":"lise gotell","count":1,"weighted_score":1.13,"ad_ids":[14983]},"53ce92f3":{"keyword":"open letter","count":1,"weighted_score":1.13,"ad_ids":[14983]},"bc07fad0":{"keyword":"ahrc chief","count":1,"weighted_score":1.13,"ad_ids":[14983]},"fd226a8b":{"keyword":"tyler shandro","count":1,"weighted_score":1.13,"ad_ids":[14983]},"1ae7a709":{"keyword":"final step","count":1,"weighted_score":1.13,"ad_ids":[14983]},"57148d4c":{"keyword":"alberta government","count":2,"weighted_score":1.2,"ad_ids":[[14983,14984]]},"0d9232e1":{"keyword":"same time","count":1,"weighted_score":1.13,"ad_ids":[14983]},"321f3bbc":{"keyword":"sexual orientation","count":1,"weighted_score":1.13,"ad_ids":[14983]},"263462e8":{"keyword":"criminal defamation","count":1,"weighted_score":1.13,"ad_ids":[14984]},"788db0a5":{"keyword":"abandoning the target","count":1,"weighted_score":1.13,"ad_ids":[14984]},"da4992a5":{"keyword":"clearer example","count":1,"weighted_score":1.13,"ad_ids":[14984]},"3134d029":{"keyword":"cancellation process","count":1,"weighted_score":1.13,"ad_ids":[14984]},"eac611d6":{"keyword":"calgary police service","count":1,"weighted_score":1.13,"ad_ids":[14984]},"1fcd1a3e":{"keyword":"harm the target","count":1,"weighted_score":1.13,"ad_ids":[14984]},"de12390c":{"keyword":"institutional betrayal","count":1,"weighted_score":1.13,"ad_ids":[14984]},"19f87981":{"keyword":"own experience","count":1,"weighted_score":1.13,"ad_ids":[14984]},"8c1d2270":{"keyword":"more lawyers","count":1,"weighted_score":1.13,"ad_ids":[14984]},"00a8c57c":{"keyword":"law society","count":1,"weighted_score":1.13,"ad_ids":[14984]},"dd60e7b6":{"keyword":"completed the dy","count":1,"weighted_score":1.13,"ad_ids":[14984]},"ae38af47":{"keyword":"accepts the canceller","count":1,"weighted_score":1.13,"ad_ids":[14984]},"700128ce":{"keyword":"make a complaint","count":1,"weighted_score":1.13,"ad_ids":[14984]},"23bc5213":{"keyword":"cancellation context","count":1,"weighted_score":1.13,"ad_ids":[14984]},"9abeba97":{"keyword":"institutional","count":1,"weighted_score":1.13,"ad_ids":[14984]},"4c44dd4d":{"keyword":"betrayal theory","count":1,"weighted_score":1.13,"ad_ids":[14984]},"ca1d3313":{"keyword":"altruistic concern","count":1,"weighted_score":1.13,"ad_ids":[14986]},"9627eac2":{"keyword":"acta psychologica","count":2,"weighted_score":1.2,"ad_ids":[14986,14989]},"572b9182":{"keyword":"released a study","count":1,"weighted_score":1.13,"ad_ids":[14986]},"bd627525":{"keyword":"entitled the association","count":1,"weighted_score":1.13,"ad_ids":[14986]},"ec5ffda5":{"keyword":"corporate management organization scholars","count":1,"weighted_score":1.13,"ad_ids":[14986]},"88a29318":{"keyword":"such people","count":1,"weighted_score":1.13,"ad_ids":[14986]},"3c894500":{"keyword":"righting a wrong","count":1,"weighted_score":1.13,"ad_ids":[14986]},"44da642e":{"keyword":"political commitments","count":1,"weighted_score":1.13,"ad_ids":[14986]},"9613dbea":{"keyword":"political zeal","count":1,"weighted_score":1.13,"ad_ids":[14986]},"a4a306d5":{"keyword":"political identity centrality","count":2,"weighted_score":1.2,"ad_ids":[14986,14989]},"058319c4":{"keyword":"most cancellers","count":1,"weighted_score":1.13,"ad_ids":[14986]},"a87f03a2":{"keyword":"political centrality identity","count":1,"weighted_score":1.13,"ad_ids":[14986]},"fe462fc4":{"keyword":"past april","count":1,"weighted_score":1.13,"ad_ids":[14986]},"dc365e79":{"keyword":"north","count":2,"weighted_score":1.2,"ad_ids":[14987,14990]},"fb731cd4":{"keyword":"human psyche","count":1,"weighted_score":1.13,"ad_ids":[14987]},"b9acf226":{"keyword":"major projects","count":1,"weighted_score":1.13,"ad_ids":[14987]},"22af2ab2":{"keyword":"additional rights","count":1,"weighted_score":1.13,"ad_ids":[14987]},"617cec10":{"keyword":"economic base","count":1,"weighted_score":1.13,"ad_ids":[14987]},"73d2e496":{"keyword":"vocal subset","count":1,"weighted_score":1.13,"ad_ids":[14987]},"0abe1b04":{"keyword":"natural resources","count":1,"weighted_score":1.13,"ad_ids":[14987]},"26e50c63":{"keyword":"recent metastasis","count":1,"weighted_score":1.13,"ad_ids":[14987]},"a9a5e0b4":{"keyword":"incremental progress","count":1,"weighted_score":1.13,"ad_ids":[14987]},"37933603":{"keyword":"are all grievance","count":1,"weighted_score":1.13,"ad_ids":[14987]},"c0eb9a0a":{"keyword":"north americans","count":1,"weighted_score":1.13,"ad_ids":[14987]},"6d3eaf2f":{"keyword":"indigenous organizations","count":1,"weighted_score":1.13,"ad_ids":[14987]},"5ebefc65":{"keyword":"native governments","count":1,"weighted_score":1.13,"ad_ids":[14987]},"db9f51b6":{"keyword":"indigenous north americans","count":1,"weighted_score":1.13,"ad_ids":[14987]},"542c6825":{"keyword":"first nations","count":1,"weighted_score":1.13,"ad_ids":[14987]},"5e0fa096":{"keyword":"darkest crevices","count":1,"weighted_score":1.13,"ad_ids":[14987]},"13d08147":{"keyword":"genuine progress","count":1,"weighted_score":1.13,"ad_ids":[14987]},"403e42b1":{"keyword":"potential violence","count":1,"weighted_score":1.13,"ad_ids":[14987]},"a98ff2e0":{"keyword":"examines the emergence","count":1,"weighted_score":1.13,"ad_ids":[14987]},"a0925c07":{"keyword":"michael melanson","count":1,"weighted_score":1.13,"ad_ids":[14987]},"2d6d0679":{"keyword":"liberal_democratic norms","count":1,"weighted_score":1.13,"ad_ids":[14988]},"8b32f8a2":{"keyword":"indigenous peoples","count":2,"weighted_score":1.2,"ad_ids":[14988,14990]},"a5949c5c":{"keyword":"privilege a minority","count":1,"weighted_score":1.13,"ad_ids":[14988]},"741184a6":{"keyword":"ethnic_racial origin","count":1,"weighted_score":1.13,"ad_ids":[14988]},"65a5bd4b":{"keyword":"radical departure","count":1,"weighted_score":1.13,"ad_ids":[14988]},"708dec24":{"keyword":"non_indigenous nation_state","count":1,"weighted_score":1.13,"ad_ids":[14988]},"91b20d00":{"keyword":"existential association","count":1,"weighted_score":1.13,"ad_ids":[14988]},"909c2720":{"keyword":"radical","count":1,"weighted_score":1.13,"ad_ids":[14988]},"82701806":{"keyword":"own in_group","count":1,"weighted_score":1.13,"ad_ids":[14989]},"bc57c983":{"keyword":"in_group members","count":1,"weighted_score":1.13,"ad_ids":[14989]},"06624c2c":{"keyword":"calling_out activities","count":1,"weighted_score":1.13,"ad_ids":[14989]},"40a058d5":{"keyword":"acta psychologica study","count":1,"weighted_score":1.13,"ad_ids":[14989]},"54de7f9d":{"keyword":"altruistic purpose","count":1,"weighted_score":1.13,"ad_ids":[14989]},"f5f67aa8":{"keyword":"changing the situation","count":1,"weighted_score":1.13,"ad_ids":[14989]},"c25c9a40":{"keyword":"harsher punishments","count":1,"weighted_score":1.13,"ad_ids":[14989]},"0a34679c":{"keyword":"virtue_signal assuming","count":1,"weighted_score":1.13,"ad_ids":[14989]},"bb039a4e":{"keyword":"is the effort","count":1,"weighted_score":1.13,"ad_ids":[14989]},"aa0fffac":{"keyword":"social vigilantism","count":1,"weighted_score":1.13,"ad_ids":[14989]},"fe1f9f50":{"keyword":"political ideology","count":1,"weighted_score":1.13,"ad_ids":[14989]},"c89d3eac":{"keyword":"american indigenous peoples","count":1,"weighted_score":1.13,"ad_ids":[14990]},"fb85368a":{"keyword":"political movement","count":1,"weighted_score":1.13,"ad_ids":[14990]},"91fd851d":{"keyword":"formal organization","count":1,"weighted_score":1.13,"ad_ids":[14990]},"6d360c21":{"keyword":"are a combination","count":1,"weighted_score":1.13,"ad_ids":[14990]},"f45c8cbc":{"keyword":"north america","count":1,"weighted_score":1.13,"ad_ids":[14990]},"fd038494":{"keyword":"political sentiment","count":1,"weighted_score":1.13,"ad_ids":[14990]},"4979ce20":{"keyword":"indigenous thinkers","count":1,"weighted_score":1.13,"ad_ids":[14990]},"3cc7979d":{"keyword":"native territory","count":1,"weighted_score":1.13,"ad_ids":[14990]},"cc493902":{"keyword":"core impulses","count":1,"weighted_score":1.13,"ad_ids":[14990]},"452f61d3":{"keyword":"seeks a return","count":1,"weighted_score":1.13,"ad_ids":[14990]}}}