{"month":"2023-10","funder":1620,"topic":"family","total_keywords":20,"keywords":{"e3a436d1":{"keyword":"cerebral palsy","count":1,"weighted_score":1.13,"ad_ids":[65590]},"116c850f":{"keyword":"experience the joys","count":1,"weighted_score":1.13,"ad_ids":[65590]},"48eee712":{"keyword":"everyday life","count":1,"weighted_score":1.13,"ad_ids":[65590]},"342de6b6":{"keyword":"share the story","count":1,"weighted_score":1.13,"ad_ids":[65590]},"490ac74c":{"keyword":"fall newsletter","count":1,"weighted_score":1.13,"ad_ids":[65590]},"0d9232e1":{"keyword":"same time","count":1,"weighted_score":1.13,"ad_ids":[65590]},"dede36f1":{"keyword":"grocery store","count":1,"weighted_score":1.13,"ad_ids":[65590]},"33607480":{"keyword":"time","count":1,"weighted_score":1.13,"ad_ids":[65590]},"d552e3fd":{"keyword":"simple pleasures","count":1,"weighted_score":1.13,"ad_ids":[65590]},"9b60b6f4":{"keyword":"hansen foundation","count":1,"weighted_score":1.13,"ad_ids":[65590]},"282d6a23":{"keyword":"create a world","count":1,"weighted_score":1.13,"ad_ids":[65590]},"5611c89e":{"keyword":"can enjoy life","count":1,"weighted_score":1.13,"ad_ids":[65590]},"106a5842":{"keyword":"help","count":1,"weighted_score":1.13,"ad_ids":[65590]},"1c36be60":{"keyword":"other child","count":1,"weighted_score":1.13,"ad_ids":[65590]},"1bdd4f18":{"keyword":"additional challenges","count":1,"weighted_score":1.13,"ad_ids":[65590]},"e0f4f767":{"keyword":"today","count":1,"weighted_score":1.13,"ad_ids":[65590]},"224863d3":{"keyword":"katie longs","count":1,"weighted_score":1.13,"ad_ids":[65590]},"ab660d74":{"keyword":"rick hansen foundation","count":1,"weighted_score":1.13,"ad_ids":[65590]},"a980f7f9":{"keyword":"four_year_old holland","count":1,"weighted_score":1.13,"ad_ids":[65590]},"4aa2346a":{"keyword":"shopping cart","count":1,"weighted_score":1.13,"ad_ids":[65590]}}}