{"month":"2024-04","funder":234,"topic":"childcare","total_keywords":21,"keywords":{"f784223c":{"keyword":"redemption centre","count":3,"weighted_score":1.26,"ad_ids":[7544,7552,7557]},"5bc89abd":{"keyword":"half_back refunds","count":1,"weighted_score":1.13,"ad_ids":[7544]},"50032176":{"keyword":"drink containers","count":2,"weighted_score":1.2,"ad_ids":[7544,7552]},"082c3a24":{"keyword":"recyclingmatters","count":3,"weighted_score":1.26,"ad_ids":[7544,7552,7557]},"0b9720cb":{"keyword":"beverage container deposits","count":3,"weighted_score":1.26,"ad_ids":[7544,7552,7557]},"2ec716e4":{"keyword":"kids","count":3,"weighted_score":1.26,"ad_ids":[7544,7552,7557]},"debe6dcd":{"keyword":"full refunds","count":3,"weighted_score":1.26,"ad_ids":[7544,7552,7557]},"c684ca0d":{"keyword":"nice reward","count":1,"weighted_score":1.13,"ad_ids":[7544]},"9c568c25":{"keyword":"empty drink containers","count":1,"weighted_score":1.13,"ad_ids":[7552]},"92771718":{"keyword":"'s a win_win","count":1,"weighted_score":1.13,"ad_ids":[7552]},"27e509bc":{"keyword":"more rewards","count":1,"weighted_score":1.13,"ad_ids":[7552]},"ff3db858":{"keyword":"petite famille","count":1,"weighted_score":1.13,"ad_ids":[7553]},"1c8b838d":{"keyword":"# recycler\u00e7arapporte","count":2,"weighted_score":1.2,"ad_ids":[7553,7555]},"77236520":{"keyword":"l\u2019 achat","count":1,"weighted_score":1.13,"ad_ids":[7555]},"54d72a85":{"keyword":"boisson vides","count":1,"weighted_score":1.13,"ad_ids":[7555]},"28e70841":{"keyword":"obtenir remboursement","count":1,"weighted_score":1.13,"ad_ids":[7555]},"862b588e":{"keyword":"encombrer espace","count":1,"weighted_score":1.13,"ad_ids":[7555]},"9296bbae":{"keyword":"space head","count":1,"weighted_score":1.13,"ad_ids":[7557]},"f2244ff4":{"keyword":"favourite drinks","count":1,"weighted_score":1.13,"ad_ids":[7557]},"18d1ea64":{"keyword":"beverage containers","count":1,"weighted_score":1.13,"ad_ids":[7557]},"81d550ce":{"keyword":"empty beverage containers","count":1,"weighted_score":1.13,"ad_ids":[7557]}}}