{
    "2023-09": {
        "total_ads": 4,
        "topics": [
            {
                "topic": "alberta",
                "weighted_count": 305.83506154674666,
                "normalized_intensity": 76.45876538668666
            },
            {
                "topic": "finance",
                "weighted_count": 230.85721053764226,
                "normalized_intensity": 57.714302634410565
            }
        ]
    },
    "2023-11": {
        "total_ads": 9,
        "topics": [
            {
                "topic": "alberta",
                "weighted_count": 657.7778625267869,
                "normalized_intensity": 73.08642916964298
            },
            {
                "topic": "community",
                "weighted_count": 420.6010347430634,
                "normalized_intensity": 46.73344830478482
            },
            {
                "topic": "digital-rights",
                "weighted_count": 98.61355349010246,
                "normalized_intensity": 10.957061498900273
            },
            {
                "topic": "finance",
                "weighted_count": 57.714302634410565,
                "normalized_intensity": 6.412700292712285
            }
        ]
    },
    "2023-12": {
        "total_ads": 10,
        "topics": [
            {
                "topic": "entertainment",
                "weighted_count": 493.4864403145598,
                "normalized_intensity": 49.348644031455976
            },
            {
                "topic": "television",
                "weighted_count": 423.8896417704364,
                "normalized_intensity": 42.38896417704364
            },
            {
                "topic": "alberta",
                "weighted_count": 135.84289502068475,
                "normalized_intensity": 13.584289502068476
            }
        ]
    },
    "2024-01": {
        "total_ads": 4,
        "topics": [
            {
                "topic": "entertainment",
                "weighted_count": 221.73563368445807,
                "normalized_intensity": 55.433908421114516
            }
        ]
    }
}