{"month":"2024-03","funder":1088,"topic":"nonprofits","total_keywords":14,"keywords":{"d4eb4e89":{"keyword":"social services","count":1,"weighted_score":1.13,"ad_ids":[26132]},"3e860f41":{"keyword":"social","count":1,"weighted_score":1.13,"ad_ids":[26132]},"1866a86f":{"keyword":"provincial budget","count":1,"weighted_score":1.13,"ad_ids":[26132]},"106a5842":{"keyword":"help","count":1,"weighted_score":1.13,"ad_ids":[26132]},"e7ca7519":{"keyword":"provincial budget 2024_25","count":1,"weighted_score":1.13,"ad_ids":[26132]},"0105631d":{"keyword":"budget 2024_25","count":1,"weighted_score":1.13,"ad_ids":[26132]},"454744d5":{"keyword":"vulnerable people","count":1,"weighted_score":1.13,"ad_ids":[26132]},"6f2e8a14":{"keyword":"communities","count":2,"weighted_score":1.2,"ad_ids":[[26132,26133]]},"e1c06246":{"keyword":"families","count":1,"weighted_score":1.13,"ad_ids":[26132]},"0af96a8e":{"keyword":"budget","count":1,"weighted_score":1.13,"ad_ids":[26132]},"9da4925c":{"keyword":"health care","count":1,"weighted_score":1.13,"ad_ids":[26133]},"db36e60e":{"keyword":"better health care","count":1,"weighted_score":1.13,"ad_ids":[26133]},"52cfaeab":{"keyword":"mental health","count":1,"weighted_score":1.13,"ad_ids":[26133]},"63bd7065":{"keyword":"life","count":1,"weighted_score":1.13,"ad_ids":[26133]}}}