{"month":"2023-11","funder":285,"topic":"transparency","total_keywords":6,"keywords":{"3e30a92d":{"keyword":"greenpeace today","count":7,"weighted_score":1.38,"ad_ids":[[26447,26448],26454,26481,26483,26493,26513]},"de80b4e4":{"keyword":"change the world_literally","count":7,"weighted_score":1.38,"ad_ids":[[26447,26448],26454,26481,26483,26493,26513]},"12ea12ea":{"keyword":"change","count":7,"weighted_score":1.38,"ad_ids":[[26447,26448],26454,26481,26483,26493,26513]},"16b22f46":{"keyword":"make this work","count":7,"weighted_score":1.38,"ad_ids":[[26447,26448],26454,26481,26483,26493,26513]},"8b48d2e2":{"keyword":"giving tuesday","count":7,"weighted_score":1.38,"ad_ids":[[26447,26448],26454,26481,26483,26493,26513]},"e0f4f767":{"keyword":"today","count":7,"weighted_score":1.38,"ad_ids":[[26447,26448],26454,26481,26483,26493,26513]}}}