[
    {
        "keyword": "energy mix",
        "week_start": "2023-08-28",
        "ad_count": 2,
        "funder_ids": [
            1195
        ],
        "keyword_hash": "c8904379"
    },
    {
        "keyword": "new eriksdale er",
        "week_start": "2023-08-28",
        "ad_count": 1,
        "funder_ids": [
            555
        ],
        "keyword_hash": "c89e6a96"
    },
    {
        "keyword": "can become part",
        "week_start": "2023-09-18",
        "ad_count": 1,
        "funder_ids": [
            133
        ],
        "keyword_hash": "c8932a7f"
    },
    {
        "keyword": "new eriksdale er",
        "week_start": "2023-09-25",
        "ad_count": 1,
        "funder_ids": [
            555
        ],
        "keyword_hash": "c89e6a96"
    },
    {
        "keyword": "energy mix",
        "week_start": "2023-10-02",
        "ad_count": 2,
        "funder_ids": [
            1195
        ],
        "keyword_hash": "c8904379"
    },
    {
        "keyword": "regarder documentaire",
        "week_start": "2023-10-09",
        "ad_count": 4,
        "funder_ids": [
            1
        ],
        "keyword_hash": "c890eb1e"
    },
    {
        "keyword": "finland determined",
        "week_start": "2023-10-16",
        "ad_count": 1,
        "funder_ids": [
            56
        ],
        "keyword_hash": "c8959c92"
    },
    {
        "keyword": "energy mix",
        "week_start": "2023-10-23",
        "ad_count": 2,
        "funder_ids": [
            1195
        ],
        "keyword_hash": "c8904379"
    },
    {
        "keyword": "viral internet",
        "week_start": "2023-10-30",
        "ad_count": 1,
        "funder_ids": [
            1
        ],
        "keyword_hash": "c896729f"
    },
    {
        "keyword": "energy mix",
        "week_start": "2023-11-06",
        "ad_count": 4,
        "funder_ids": [
            1195
        ],
        "keyword_hash": "c8904379"
    },
    {
        "keyword": "nwt is stagnant",
        "week_start": "2023-11-06",
        "ad_count": 1,
        "funder_ids": [
            1684
        ],
        "keyword_hash": "c899f05d"
    },
    {
        "keyword": "thomas pesquet",
        "week_start": "2023-11-20",
        "ad_count": 1,
        "funder_ids": [
            1
        ],
        "keyword_hash": "c89df0e1"
    },
    {
        "keyword": "energy mix",
        "week_start": "2023-11-27",
        "ad_count": 7,
        "funder_ids": [
            1
        ],
        "keyword_hash": "c8904379"
    },
    {
        "keyword": "free hiv resources",
        "week_start": "2023-11-27",
        "ad_count": 1,
        "funder_ids": [
            318
        ],
        "keyword_hash": "c89f5df6"
    },
    {
        "keyword": "energy mix",
        "week_start": "2023-12-04",
        "ad_count": 27,
        "funder_ids": [
            286,
            1195
        ],
        "keyword_hash": "c8904379"
    },
    {
        "keyword": "# instaislam",
        "week_start": "2023-12-04",
        "ad_count": 1,
        "funder_ids": [
            1
        ],
        "keyword_hash": "c89d9d11"
    },
    {
        "keyword": "energy mix",
        "week_start": "2023-12-18",
        "ad_count": 2,
        "funder_ids": [
            286
        ],
        "keyword_hash": "c8904379"
    },
    {
        "keyword": "# instaislam",
        "week_start": "2023-12-18",
        "ad_count": 1,
        "funder_ids": [
            1
        ],
        "keyword_hash": "c89d9d11"
    },
    {
        "keyword": "obsessive hours",
        "week_start": "2023-12-18",
        "ad_count": 1,
        "funder_ids": [
            1
        ],
        "keyword_hash": "c89a920e"
    },
    {
        "keyword": "water bottling more",
        "week_start": "2024-01-01",
        "ad_count": 1,
        "funder_ids": [
            124
        ],
        "keyword_hash": "c896a1ac"
    },
    {
        "keyword": "energy mix",
        "week_start": "2024-01-08",
        "ad_count": 24,
        "funder_ids": [
            286
        ],
        "keyword_hash": "c8904379"
    },
    {
        "keyword": "water bottling more",
        "week_start": "2024-01-08",
        "ad_count": 1,
        "funder_ids": [
            124
        ],
        "keyword_hash": "c896a1ac"
    },
    {
        "keyword": "share knowledge",
        "week_start": "2024-01-15",
        "ad_count": 1,
        "funder_ids": [
            1
        ],
        "keyword_hash": "c8974722"
    },
    {
        "keyword": "canada announcement",
        "week_start": "2024-01-22",
        "ad_count": 2,
        "funder_ids": [
            764
        ],
        "keyword_hash": "c894a47c"
    },
    {
        "keyword": "energy mix",
        "week_start": "2024-01-29",
        "ad_count": 5,
        "funder_ids": [
            286
        ],
        "keyword_hash": "c8904379"
    },
    {
        "keyword": "highest canadian standards",
        "week_start": "2024-01-29",
        "ad_count": 2,
        "funder_ids": [
            32
        ],
        "keyword_hash": "c895d9c8"
    },
    {
        "keyword": "investment value",
        "week_start": "2024-01-29",
        "ad_count": 1,
        "funder_ids": [
            1
        ],
        "keyword_hash": "c89bd01e"
    },
    {
        "keyword": "airrow bulletin",
        "week_start": "2024-02-05",
        "ad_count": 1,
        "funder_ids": [
            1
        ],
        "keyword_hash": "c890e72b"
    },
    {
        "keyword": "mais bien d'une baisse du fardeau",
        "week_start": "2024-02-19",
        "ad_count": 1,
        "funder_ids": [
            188
        ],
        "keyword_hash": "c8912dac"
    },
    {
        "keyword": "jeopardize the coverage quality",
        "week_start": "2024-02-26",
        "ad_count": 1,
        "funder_ids": [
            259
        ],
        "keyword_hash": "c898199e"
    },
    {
        "keyword": "ease tax stress",
        "week_start": "2024-03-11",
        "ad_count": 1,
        "funder_ids": [
            1227
        ],
        "keyword_hash": "c89d6a45"
    },
    {
        "keyword": "energy mix",
        "week_start": "2024-03-25",
        "ad_count": 90,
        "funder_ids": [
            286
        ],
        "keyword_hash": "c8904379"
    },
    {
        "keyword": "palm oil",
        "week_start": "2024-03-25",
        "ad_count": 1,
        "funder_ids": [
            1
        ],
        "keyword_hash": "c89a39a8"
    },
    {
        "keyword": "energy mix",
        "week_start": "2024-04-01",
        "ad_count": 9,
        "funder_ids": [
            286
        ],
        "keyword_hash": "c8904379"
    },
    {
        "keyword": "palm oil",
        "week_start": "2024-04-01",
        "ad_count": 1,
        "funder_ids": [
            1
        ],
        "keyword_hash": "c89a39a8"
    },
    {
        "keyword": "energy mix",
        "week_start": "2024-04-15",
        "ad_count": 19,
        "funder_ids": [
            286
        ],
        "keyword_hash": "c8904379"
    },
    {
        "keyword": "d\u00e9couvrez l' histoire",
        "week_start": "2024-04-22",
        "ad_count": 1,
        "funder_ids": [
            942
        ],
        "keyword_hash": "c89875f3"
    },
    {
        "keyword": "embodying the nation",
        "week_start": "2024-04-22",
        "ad_count": 1,
        "funder_ids": [
            1
        ],
        "keyword_hash": "c896b3cd"
    },
    {
        "keyword": "regenerative agriculture techniques",
        "week_start": "2024-05-13",
        "ad_count": 1,
        "funder_ids": [
            118
        ],
        "keyword_hash": "c899fa84"
    },
    {
        "keyword": "preserve the value",
        "week_start": "2024-05-20",
        "ad_count": 1,
        "funder_ids": [
            764
        ],
        "keyword_hash": "c89eba92"
    },
    {
        "keyword": "energy mix",
        "week_start": "2024-05-27",
        "ad_count": 1,
        "funder_ids": [
            229
        ],
        "keyword_hash": "c8904379"
    },
    {
        "keyword": "energy mix",
        "week_start": "2024-06-10",
        "ad_count": 36,
        "funder_ids": [
            286
        ],
        "keyword_hash": "c8904379"
    },
    {
        "keyword": "climate initiative",
        "week_start": "2024-06-10",
        "ad_count": 1,
        "funder_ids": [
            645
        ],
        "keyword_hash": "c8979452"
    },
    {
        "keyword": "energy mix",
        "week_start": "2024-06-17",
        "ad_count": 25,
        "funder_ids": [
            286
        ],
        "keyword_hash": "c8904379"
    },
    {
        "keyword": "palm oil",
        "week_start": "2024-06-17",
        "ad_count": 1,
        "funder_ids": [
            1
        ],
        "keyword_hash": "c89a39a8"
    },
    {
        "keyword": "energy mix",
        "week_start": "2024-06-24",
        "ad_count": 2,
        "funder_ids": [
            229,
            286
        ],
        "keyword_hash": "c8904379"
    },
    {
        "keyword": "palm oil",
        "week_start": "2024-06-24",
        "ad_count": 1,
        "funder_ids": [
            132
        ],
        "keyword_hash": "c89a39a8"
    },
    {
        "keyword": "morneau shepell",
        "week_start": "2024-07-01",
        "ad_count": 2,
        "funder_ids": [
            323
        ],
        "keyword_hash": "c897590d"
    },
    {
        "keyword": "energy mix",
        "week_start": "2024-07-08",
        "ad_count": 3,
        "funder_ids": [
            286
        ],
        "keyword_hash": "c8904379"
    },
    {
        "keyword": "darcy tuckey",
        "week_start": "2024-07-08",
        "ad_count": 1,
        "funder_ids": [
            130
        ],
        "keyword_hash": "c89cb7c3"
    },
    {
        "keyword": "morneau shepell",
        "week_start": "2024-07-08",
        "ad_count": 1,
        "funder_ids": [
            323
        ],
        "keyword_hash": "c897590d"
    },
    {
        "keyword": "energy mix",
        "week_start": "2024-07-15",
        "ad_count": 1,
        "funder_ids": [
            229
        ],
        "keyword_hash": "c8904379"
    },
    {
        "keyword": "morneau shepell",
        "week_start": "2024-07-15",
        "ad_count": 1,
        "funder_ids": [
            192
        ],
        "keyword_hash": "c897590d"
    },
    {
        "keyword": "doug",
        "week_start": "2024-07-15",
        "ad_count": 1,
        "funder_ids": [
            1
        ],
        "keyword_hash": "c898ab69"
    },
    {
        "keyword": "doug",
        "week_start": "2024-07-22",
        "ad_count": 33,
        "funder_ids": [
            1
        ],
        "keyword_hash": "c898ab69"
    },
    {
        "keyword": "energy mix",
        "week_start": "2024-07-29",
        "ad_count": 1,
        "funder_ids": [
            229
        ],
        "keyword_hash": "c8904379"
    },
    {
        "keyword": "partners are desperate",
        "week_start": "2024-07-29",
        "ad_count": 1,
        "funder_ids": [
            1
        ],
        "keyword_hash": "c8972e31"
    },
    {
        "keyword": "palm oil",
        "week_start": "2024-08-05",
        "ad_count": 1,
        "funder_ids": [
            1
        ],
        "keyword_hash": "c89a39a8"
    },
    {
        "keyword": "energy mix",
        "week_start": "2024-08-12",
        "ad_count": 1,
        "funder_ids": [
            229
        ],
        "keyword_hash": "c8904379"
    },
    {
        "keyword": "ensures all patients",
        "week_start": "2024-08-12",
        "ad_count": 4,
        "funder_ids": [
            794
        ],
        "keyword_hash": "c89c4a23"
    },
    {
        "keyword": "marine theft takedown",
        "week_start": "2024-08-12",
        "ad_count": 1,
        "funder_ids": [
            118
        ],
        "keyword_hash": "c892b45b"
    },
    {
        "keyword": "investment value",
        "week_start": "2024-08-19",
        "ad_count": 5,
        "funder_ids": [
            1
        ],
        "keyword_hash": "c89bd01e"
    },
    {
        "keyword": "entertainment events",
        "week_start": "2024-08-19",
        "ad_count": 1,
        "funder_ids": [
            1
        ],
        "keyword_hash": "c891f767"
    },
    {
        "keyword": "ensures all patients",
        "week_start": "2024-08-26",
        "ad_count": 2,
        "funder_ids": [
            794
        ],
        "keyword_hash": "c89c4a23"
    }
]